Codes and results/comp.v
`timescale 1ns / 1ps

module comp(input [3:0] gSign, input [3:0] cutSign, input enable, output y);
wire [3:0] en; 
assign en  = {enable, enable, enable, enable};
wire [3:0] x0;
wire x1;
assign x0 = gSign ^ cutSign;
assign x1 = x0[0] | x0[1] | x0[2] | x0[3];
and(y,x1,enable);
endmodule

Codes and results/sir.v
`timescale 1ns / 1ps
module sir (input clk,enable, reset,y, output reg [3:0] q);

reg [2:0] temp;
initial q = 4'b0;

always @ (posedge clk) // start generating when enable = 1 by setting check to 1
begin
	if (clk == 1) begin
	temp[0] = q[0] ^ y; // store it temporarily to later assign without clashing with cache update
	temp[1] = q[0] ^ q[3];
	temp[2] = q[0] ^ q[1];

	q[1] <= q[2];
	q[2] <= temp[1];
	q[3] <= temp[0];
	q[0] <= temp[2];
end
	if (reset == 1)	q <= 4'b0;
end

//$display("%b %b %b %b %b",a,b,c,d,y);
endmodule

Codes and results/cut.v
`timescale 1ns / 1ps
module cut (input [2:0] a,input [11:0] check,input value,output y); //atmost one saf
wire aa,b,c,w1,w2,w3,w4,w5,w6,w7,w8,w9,w10,w11,w12,w13;

assign aa = (check[0]==1) ? value: a[0];
assign b = (check[1]==1) ? value: a[1];
assign c = (check[2]==1) ? value: a[2];
assign w1 = (check[3]==1) ? value: aa;
assign w2 = (check[4]==1) ? value: b;
assign w3 = (check[5]==1) ? value: b;
assign w4 = (check[6]==1) ? value: b;
assign w5 = (check[7]==1) ? value: c;
assign w6 = (check[8]==1) ? value: w1 | w2;
assign w7 = (check[9]==1) ? value: (w4 & w5);
assign w8 = (check[10]==1) ? value: (w3 | w6);
assign w9 = (check[11]==1) ? value: (w7 & w8);
assign y = w9;
//$display("%b %b %b %b %b",a,b,c,d,y);
endmodule

Codes and results/mux.v
`timescale 1ns / 1ps

module mux(input [2:0] primary, input [2:0] test, input enable, output [2:0] y);

wire [2:0] en; 
assign en = {enable, enable, enable};
wire [2:0] enNot, out1, out2;

assign enNot = ~en;
assign out1 = primary & enNot;
assign out2 = test & en;
assign y = out1 | out2;

endmodule

Codes and results/pgen.v
`timescale 1ns / 1ps
module pgen (input clk, enable, reset, output reg [2:0] q);

reg temp;
initial q = 3'b101;

always @ (posedge clk) // start generating when enable = 1 by setting check to 1
begin
	if (enable == 1'b1 && reset == 1'b0)
	begin
	temp = q[1] ^ q[2]; // store it temporarily to later assign without clashing with cache update
	q[2] <= q[1];
	q[1] <= q[0];
	q[0] <= temp;
	end
	else if (reset == 1'b1) q <= 3'b110;
end

//$display("%b %b %b %b %b",a,b,c,d,y);
endmodule

Codes and results/alu.v
`timescale 1ns / 1ps
`include "pgen.v"
`include "mux.v"
`include "cut.v"
`include "sir.v"
`include "comp.v"

module alu(input [2:0] in, input clk, reset, enable, input [11:0] check, input value, output y,e);
// 3 inputs,clk,reset , cl output, fault detector

// initiate Pattern Gen blocks
// Let output be [2:0]p
wire [2:0] p;
pgen p1 (clk, enable, reset, p);

// initiate muxes
// outputs ym1, ym2
wire [2:0] ym1, ym2;
mux m1 (in,p,enable,ym1); // to fault-free
mux m2 (in,p,enable,ym2); // to faulty ckt

// execute the combinational logic
// outputs: yc1, yc2
wire yc1, yc2;
cut c1 (ym2,12'b0,1'b0,yc1); // golden
cut c3 (in,12'b0,1'b0,y); // golden
cut c2 (ym1,check,value,yc2); // faulty 

// signature register
// Let outputs be ys1, ys2
wire [3:0] ys1, ys2; // size should be changed. 7 values collected and 4 values are observed
sir s1 (clk,enable,reset,yc1, ys1); // golden
sir s2 (clk,enable,reset,yc2, ys2); // faulty

// comparator
comp c11 (ys1, ys2, enable, e);

//$display("%b %b %b %b %b",a,b,c,d,y);
endmodule

Codes and results/alu_t.v
// Test bench for the combinational logic circuit
`include "alu.v"
module test_bench();

// Inputs
reg [2:0] in;
reg [11:0] check;
reg clk,reset,enable,value;

// Variables
integer i,j;

// Outputs	
wire y,e;

// Instantiate the Unit Under Test (UUT)
alu uut (in,clk,reset,enable,check,value,y,e);

always #5  clk = ~clk ;//setup clk
initial begin
	// Initialize Inputs
	$dumpfile("test_bench.vcd");
	$dumpvars;

	// initialise all the wires
	reset = 1'b0;
	enable = 1'b1;
	value = 1'b0;
	check = 12'b0;
	clk = 0;
	in = 3'b110;

	#5 // se3tting wire B sa1
	check = 12'b000000000010;
//	enable = 1'b1;
	value = 1;
	#100

	// reset the wires
	reset = ~reset;
	#5
	reset = ~reset;

	#5 // setting ckt fault free
	check = 12'b0;
	#100
	$finish;
/*
	// reset the wires
	reset = ~reset;
	#5
	reset = ~reset;

	#5 // setting wire w9  to sa1
	check = 9'b100000000;
	value = 0;

	#100
*/
end
endmodule

Codes and results/test_bench.vcd
$date
	Tue Dec  7 22:32:24 2021
$end
$version
	Icarus Verilog
$end
$timescale
	1ps
$end
$scope module test_bench $end
$var wire 1 ! y $end
$var wire 1 " e $end
$var reg 12 # check [11:0] $end
$var reg 1 $ clk $end
$var reg 1 % enable $end
$var reg 3 & in [2:0] $end
$var reg 1 ' reset $end
$var reg 1 ( value $end
$scope module uut $end
$var wire 12 ) check [11:0] $end
$var wire 1 $ clk $end
$var wire 1 % enable $end
$var wire 3 * in [2:0] $end
$var wire 1 ' reset $end
$var wire 1 ( value $end
$var wire 4 + ys2 [3:0] $end
$var wire 4 , ys1 [3:0] $end
$var wire 3 - ym2 [2:0] $end
$var wire 3 . ym1 [2:0] $end
$var wire 1 / yc2 $end
$var wire 1 0 yc1 $end
$var wire 1 ! y $end
$var wire 3 1 p [2:0] $end
$var wire 1 " e $end
$scope module c1 $end
$var wire 12 2 check [11:0] $end
$var wire 1 3 value $end
$var wire 1 0 y $end
$var wire 1 4 w9 $end
$var wire 1 5 w8 $end
$var wire 1 6 w7 $end
$var wire 1 7 w6 $end
$var wire 1 8 w5 $end
$var wire 1 9 w4 $end
$var wire 1 : w3 $end
$var wire 1 ; w2 $end
$var wire 1 < w1 $end
$var wire 1 = c $end
$var wire 1 > b $end
$var wire 1 ? aa $end
$var wire 3 @ a [2:0] $end
$upscope $end
$scope module c11 $end
$var wire 1 % enable $end
$var wire 4 A x0 [3:0] $end
$var wire 1 B x1 $end
$var wire 1 " y $end
$var wire 4 C gSign [3:0] $end
$var wire 4 D en [3:0] $end
$var wire 4 E cutSign [3:0] $end
$upscope $end
$scope module c2 $end
$var wire 12 F check [11:0] $end
$var wire 1 ( value $end
$var wire 1 / y $end
$var wire 1 G w9 $end
$var wire 1 H w8 $end
$var wire 1 I w7 $end
$var wire 1 J w6 $end
$var wire 1 K w5 $end
$var wire 1 L w4 $end
$var wire 1 M w3 $end
$var wire 1 N w2 $end
$var wire 1 O w1 $end
$var wire 1 P c $end
$var wire 1 Q b $end
$var wire 1 R aa $end
$var wire 3 S a [2:0] $end
$upscope $end
$scope module c3 $end
$var wire 3 T a [2:0] $end
$var wire 12 U check [11:0] $end
$var wire 1 V value $end
$var wire 1 ! y $end
$var wire 1 W w9 $end
$var wire 1 X w8 $end
$var wire 1 Y w7 $end
$var wire 1 Z w6 $end
$var wire 1 [ w5 $end
$var wire 1 \ w4 $end
$var wire 1 ] w3 $end
$var wire 1 ^ w2 $end
$var wire 1 _ w1 $end
$var wire 1 ` c $end
$var wire 1 a b $end
$var wire 1 b aa $end
$upscope $end
$scope module m1 $end
$var wire 3 c enNot [2:0] $end
$var wire 1 % enable $end
$var wire 3 d out1 [2:0] $end
$var wire 3 e out2 [2:0] $end
$var wire 3 f primary [2:0] $end
$var wire 3 g y [2:0] $end
$var wire 3 h test [2:0] $end
$var wire 3 i en [2:0] $end
$upscope $end
$scope module m2 $end
$var wire 3 j enNot [2:0] $end
$var wire 1 % enable $end
$var wire 3 k out1 [2:0] $end
$var wire 3 l out2 [2:0] $end
$var wire 3 m primary [2:0] $end
$var wire 3 n y [2:0] $end
$var wire 3 o test [2:0] $end
$var wire 3 p en [2:0] $end
$upscope $end
$scope module p1 $end
$var wire 1 $ clk $end
$var wire 1 % enable $end
$var wire 1 ' reset $end
$var reg 3 q q [2:0] $end
$var reg 1 r temp $end
$upscope $end
$scope module s1 $end
$var wire 1 $ clk $end
$var wire 1 % enable $end
$var wire 1 ' reset $end
$var wire 1 0 y $end
$var reg 4 s q [3:0] $end
$var reg 3 t temp [2:0] $end
$upscope $end
$scope module s2 $end
$var wire 1 $ clk $end
$var wire 1 % enable $end
$var wire 1 ' reset $end
$var wire 1 / y $end
$var reg 4 u q [3:0] $end
$var reg 3 v temp [2:0] $end
$upscope $end
$upscope $end
$upscope $end
$enddefinitions $end
#0
$dumpvars
bx v
b0 u
bx t
b0 s
xr
b101 q
b111 p
b101 o
b101 n
b110 m
b101 l
b0 k
b0 j
b111 i
b101 h
b101 g
b110 f
b101 e
b0 d
b0 c
0b
1a
1`
0_
1^
1]
1\
1[
1Z
1Y
1X
1W
0V
b0 U
b110 T
b101 S
1R
0Q
1P
1O
0N
0M
0L
1K
1J
0I
1H
0G
b0 F
b0 E
b1111 D
b0 C
0B
b0 A
b101 @
1?
0>
1=
1<
0;
0:
09
18
17
06
15
04
03
b0 2
b101 1
00
0/
b101 .
b101 -
b0 ,
b0 +
b110 *
b0 )
0(
0'
b110 &
1%
0$
b0 #
0"
1!
$end
#5000
08
1;
1:
19
0K
0=
1>
0P
b11 -
b11 @
b11 n
b11 .
b11 S
b11 g
b11 l
b11 e
b11 1
b11 h
b11 o
b11 q
0/
0G
0I
1N
1M
1L
1Q
1r
b0 t
b0 v
1(
b10 #
b10 )
b10 F
1$
#10000
0$
#15000
10
14
1/
1G
16
1I
18
1K
1=
1P
b111 -
b111 @
b111 n
b111 .
b111 S
b111 g
b111 l
b111 e
b111 1
b111 h
b111 o
b111 q
1$
#20000
0$
#25000
0<
0O
0?
0R
b110 -
b110 @
b110 n
b110 .
b110 S
b110 g
b110 l
b110 e
b110 1
b110 h
b110 o
b110 q
b1000 ,
b1000 C
b1000 s
b1000 +
b1000 E
b1000 u
0r
b1 t
b1 v
1$
#30000
0$
#35000
05
00
04
07
06
0;
0:
09
0>
b100 -
b100 @
b100 n
b100 .
b100 S
b100 g
b100 l
b100 e
b1100 +
b1100 E
b1100 u
b1100 ,
b1100 C
b1100 s
b100 1
b100 h
b100 o
b100 q
b11 v
b11 t
1$
#40000
0$
#45000
15
0/
0G
17
0I
08
1<
0K
1O
0=
1?
0P
1R
1"
1B
b1 -
b1 @
b1 n
b1 .
b1 S
b1 g
b1 l
b1 e
b1000 A
b1 1
b1 h
b1 o
b1 q
b110 ,
b110 C
b110 s
b1110 +
b1110 E
b1110 u
1r
b10 t
1$
#50000
0$
#55000
1;
1:
19
0<
0O
1"
1>
0?
0R
1B
b10 -
b10 @
b10 n
b10 .
b10 S
b10 g
b100 A
b10 l
b10 e
b111 +
b111 E
b111 u
b11 ,
b11 C
b11 s
b10 1
b10 h
b10 o
b10 q
b110 v
b100 t
0r
1$
#60000
0$
#65000
1/
1G
1I
18
0;
0:
09
1<
1K
1O
1"
1=
0>
1?
1P
1R
1B
b101 -
b101 @
b101 n
b101 .
b101 S
b101 g
b101 l
b101 e
b10 A
b101 1
b101 h
b101 o
b101 q
b1100 ,
b1100 C
b1100 s
b1110 +
b1110 E
b1110 u
1r
b11 t
b11 v
1$
#70000
0$
#75000
0/
0G
0I
08
1;
1:
19
0K
0=
1>
0P
b11 -
b11 @
b11 n
b11 .
b11 S
b11 g
b1001 A
b11 l
b11 e
b1111 +
b1111 E
b1111 u
b110 ,
b110 C
b110 s
b11 1
b11 h
b11 o
b11 q
b111 v
b10 t
1$
#80000
0$
#85000
10
14
1/
1G
16
1I
18
1K
1=
1P
b111 -
b111 @
b111 n
b111 .
b111 S
b111 g
b111 l
b111 e
b111 1
b111 h
b111 o
b111 q
b11 ,
b11 C
b11 s
b1010 +
b1010 E
b1010 u
b100 t
b1 v
1$
#90000
0$
#95000
0<
0O
0?
0R
b110 -
b110 @
b110 n
b110 .
b110 S
b110 g
b110 l
b110 e
b1101 +
b1101 E
b1101 u
b100 ,
b100 C
b100 s
b110 1
b110 h
b110 o
b110 q
b111 v
b10 t
0r
1$
#100000
0$
#105000
0"
0B
b0 A
b0 ,
b0 C
b0 s
b0 +
b0 E
b0 u
b1 t
b100 v
1$
1'
#110000
0$
0'
#115000
05
00
04
0H
0/
0G
07
06
0J
0I
0;
0:
09
0N
0M
0L
0>
0Q
b100 -
b100 @
b100 n
b100 .
b100 S
b100 g
b100 l
b100 e
b1000 +
b1000 E
b1000 u
b1000 ,
b1000 C
b1000 s
b100 1
b100 h
b100 o
b100 q
b1 v
1$
b0 #
b0 )
b0 F
#120000
0$
#125000
15
1H
17
1J
08
1<
0K
1O
0=
1?
0P
1R
b1 -
b1 @
b1 n
b1 .
b1 S
b1 g
b1 l
b1 e
b1 1
b1 h
b1 o
b1 q
b100 ,
b100 C
b100 s
b100 +
b100 E
b100 u
1r
b10 t
b10 v
1$
#130000
0$
#135000
1;
1:
19
0<
1N
1M
1L
0O
1>
0?
1Q
0R
b10 -
b10 @
b10 n
b10 .
b10 S
b10 g
b10 l
b10 e
b10 +
b10 E
b10 u
b10 ,
b10 C
b10 s
b10 1
b10 h
b10 o
b10 q
b0 v
b0 t
0r
1$
#140000
0$
#145000
18
0;
0:
09
1<
1K
0N
0M
0L
1O
1=
0>
1?
1P
0Q
1R
b101 -
b101 @
b101 n
b101 .
b101 S
b101 g
b101 l
b101 e
b101 1
b101 h
b101 o
b101 q
b1 ,
b1 C
b1 s
b1 +
b1 E
b1 u
1r
b100 t
b100 v
1$
#150000
0$
#155000
08
1;
1:
19
0K
1N
1M
1L
0=
1>
0P
1Q
b11 -
b11 @
b11 n
b11 .
b11 S
b11 g
b11 l
b11 e
b1101 +
b1101 E
b1101 u
b1101 ,
b1101 C
b1101 s
b11 1
b11 h
b11 o
b11 q
b111 v
b111 t
1$
#160000
0$
#165000
10
14
1/
1G
16
1I
18
1K
1=
1P
b111 -
b111 @
b111 n
b111 .
b111 S
b111 g
b111 l
b111 e
b111 1
b111 h
b111 o
b111 q
b1011 ,
b1011 C
b1011 s
b1011 +
b1011 E
b1011 u
b101 t
b101 v
1$
#170000
0$
#175000
0<
0O
0?
0R
b110 -
b110 @
b110 n
b110 .
b110 S
b110 g
b110 l
b110 e
b0 +
b0 E
b0 u
b0 ,
b0 C
b0 s
b110 1
b110 h
b110 o
b110 q
b0 v
b0 t
0r
1$
#180000
0$
#185000
05
00
04
0H
0/
0G
07
06
0J
0I
0;
0:
09
0N
0M
0L
0>
0Q
b100 -
b100 @
b100 n
b100 .
b100 S
b100 g
b100 l
b100 e
b100 1
b100 h
b100 o
b100 q
b1000 ,
b1000 C
b1000 s
b1000 +
b1000 E
b1000 u
b1 t
b1 v
1$
#190000
0$
#195000
15
1H
17
1J
08
1<
0K
1O
0=
1?
0P
1R
b1 -
b1 @
b1 n
b1 .
b1 S
b1 g
b1 l
b1 e
b100 +
b100 E
b100 u
b100 ,
b100 C
b100 s
b1 1
b1 h
b1 o
b1 q
b10 v
b10 t
1r
1$
#200000
0$
#205000
1;
1:
19
0<
1N
1M
1L
0O
1>
0?
1Q
0R
b10 -
b10 @
b10 n
b10 .
b10 S
b10 g
b10 l
b10 e
b10 1
b10 h
b10 o
b10 q
b10 ,
b10 C
b10 s
b10 +
b10 E
b10 u
0r
b0 t
b0 v
1$
#210000
0$
#215000
18
0;
0:
09
1<
1K
0N
0M
0L
1O
1=
0>
1?
1P
0Q
1R
b101 -
b101 @
b101 n
b101 .
b101 S
b101 g
b101 l
b101 e
b1 +
b1 E
b1 u
b1 ,
b1 C
b1 s
b101 1
b101 h
b101 o
b101 q
b100 v
b100 t
1r
1$
